Workbook

Sheet Salary_niit
A1: S/N | B1: EMPLOYEE NAMES | C1: EMPLOY ID | D1: STATE | E1: SEX | F1: DEPT | G1: STATUS | H1: GRADE | I1: HIRED DATE | J1: BASIC SALARY | K1: WARD ALL | L1: MED/ALL | M1: T/ALL | N1: GROSS BENEFITS | O1: ANNUAL SALARY | P1: TAX | Q1: ANNUAL-80%LOAN | R1: MONTHLY RE-PAY-6.6% | S1: GROSS LIABILITIES | T1: TAX + MONTHLY REPAY-6.6% | U1: NET SALARY
A2: 50 | B2: OLANIYI | C2: 00-849 | D2: ABIA | E2: M | F2: CREDIT | G2: MARRIED | H2: TRAINEE | I2: 43956 | J2: 100000 | K2: 2000 | L2: 500 | M2: 100 | N2: 2600 | O2: 1200000 | P2: 10000 | Q2: 960000 | R2: 6600 | S2: 976600 | T2: 16600 | U2: 1183400
A3: 51 | B3: TOBI | C3: 00-850 | D3: ABIA | E3: F | F3: CREDIT | G3: SINGLE | H3: TRAINEE | I3: 43956 | J3: 100000 | K3: 2000 | L3: 500 | M3: 100 | N3: 2600 | O3: 1200000 | P3: 10000 | Q3: 960000 | R3: 6600 | S3: 976600 | T3: 16600 | U3: 1183400
A4: 52 | B4: ELEAS | C4: 00-851 | D4: ABIA | E4: F | F4: CREDIT | G4: SINGLE | H4: TRAINEE | I4: 43956 | J4: 100000 | K4: 2000 | L4: 500 | M4: 100 | N4: 2600 | O4: 1200000 | P4: 10000 | Q4: 960000 | R4: 6600 | S4: 976600 | T4: 16600 | U4: 1183400
A5: 52 | B5: ELEAS | C5: 00-851 | D5: ABIA | E5: F | F5: CREDIT | G5: SINGLE | H5: TRAINEE | I5: 43956 | J5: 100000 | K5: 2000 | L5: 500 | M5: 100 | N5: 2600 | O5: 1200000 | P5: 10000 | Q5: 960000 | R5: 6600 | S5: 976600 | T5: 16600 | U5: 1183400
A6: 53 | B6: NICK | C6: 00-852 | D6: ABIA | E6: M | F6: CREDIT | G6: MARRIED | H6: TRAINEE | I6: 43542 | J6: 100000 | K6: 2000 | L6: 500 | M6: 100 | N6: 2600 | O6: 1200000 | P6: 10000 | Q6: 960000 | R6: 6600 | S6: 976600 | T6: 16600 | U6: 1183400
A7: 54 | B7: MAVIN | C7: 00-853 | D7: ABIA | E7: F | F7: CREDIT | G7: SINGLE | H7: TRAINEE | I7: 43542 | J7: 100000 | K7: 2000 | L7: 500 | M7: 100 | N7: 2600 | O7: 1200000 | P7: 10000 | Q7: 960000 | R7: 6600 | S7: 976600 | T7: 16600 | U7: 1183400
A8: 55 | B8: CHINWE | C8: 00-854 | D8: ABIA | E8: F | F8: CREDIT | G8: MARRIED | H8: TRAINEE | I8: 43542 | J8: 100000 | K8: 2000 | L8: 500 | M8: 100 | N8: 2600 | O8: 1200000 | P8: 10000 | Q8: 960000 | R8: 6600 | S8: 976600 | T8: 16600 | U8: 1183400
A9: 7 | B9: VERO | C9: 00-806 | D9: ABIA | E9: M | F9: MARKETING | G9: SINGLE | H9: MANAGER | I9: 42622 | J9: 200000 | K9: 4000 | L9: 1000 | M9: 200 | N9: 5200 | O9: 2400000 | P9: 20000 | Q9: 1920000 | R9: 13200 | S9: 1953200 | T9: 33200 | U9: 2366800
A10: 65 | B10: RITA | C10: 00-864 | D10: ABIA | E10: F | F10: OPERATIONS | G10: MARRIED | H10: SNR. OFFICER | I10: 43542 | J10: 150000 | K10: 3000 | L10: 750 | M10: 150 | N10: 3900 | O10: 1800000 | P10: 15000 | Q10: 1440000 | R10: 9900 | S10: 1464900 | T10: 24900 | U10: 1775100
A11: 35 | B11: EMEKA | C11: 00-834 | D11: ABIA | E11: M | F11: SECURITY | G11: SINGLE | H11: OFFICER | I11: 43437 | J11: 120000 | K11: 2400 | L11: 600 | M11: 120 | N11: 3120 | O11: 1440000 | P11: 12000 | Q11: 1152000 | R11: 7920 | S11: 1171920 | T11: 19920 | U11: 1420080
A12: 21 | B12: DORCAS | C12: 00-820 | D12: ABUJA | E12: F | F12: MARKETING | G12: MARRIED | H12: OFFICER | I12: 44453 | J12: 120000 | K12: 2400 | L12: 600 | M12: 120 | N12: 3120 | O12: 1440000 | P12: 12000 | Q12: 1152000 | R12: 7920 | S12: 1171920 | T12: 19920 | U12: 1420080
A13: 87 | B13: CHIMEZIE | C13: 00-886 | D13: ABUJA | E13: M | F13: MARKETING | G13: MARRIED | H13: MANAGER | I13: 43542 | J13: 200000 | K13: 4000 | L13: 1000 | M13: 200 | N13: 5200 | O13: 2400000 | P13: 20000 | Q13: 1920000 | R13: 13200 | S13: 1953200 | T13: 33200 | U13: 2366800
... A152: 31 | B152: EJIOFOR | C152: 00-830 | D152: ZAMFARA | E152: M | F152: MARKETING | G152: MARRIED | H152: OFFICER | I152: 43437 | J152: 120000 | K152: 2400 | L152: 600 | M152: 120 | N152: 3120 | O152: 1440000 | P152: 12000 | Q152: 1152000 | R152: 7920 | S152: 1171920 | T152: 19920 | U152: 1420080

Sheet DASHBOARD
B5: S/N | C5: ANALYSIS QUESTIONS
B6: 1 | C6: How many employees have their names recorded in the data set | D6: =COUNTA(Salary_niit!B2:B152) -> 151
B8: 2 | C8: What is the total basic salary paid to all employees? | D8: =SUM(Salary_niit!J2:J152) -> 19550000
B10: 3 | C10: What is the total loan repayment made by all employees | D10: =SUM(Salary_niit!R2:R152) -> 1290300
B12: 4 | C12: What is the average tax paid by employees? | D12: =AVERAGEA(Salary_niit!P2:P152) -> 12947.02
B14: 5 | C14: What is the total basic salary of male employees | D14: =SUMIF(Salary_niit!E2:E152,Salary_niit!E138,Salary_niit!J2:J152) -> 12005000
A15: =A15:A26 -> 0
B16: 6 | C16: What is the total tax paid by employees in the Audit department? | D16: =SUMIF(Salary_niit!F2:F152,Salary_niit!F104,Salary_niit!P2:P152) -> 210000
B18: 7 | C18: How many employees have a annual salary greater than ₦1,200,000? | D18: =COUNTIF(Salary_niit!U2:U152,">1200000") -> 110
B20: 8 | C20: How many employees work in the marketing department? | D20: =COUNTIF(Salary_niit!F2:F152,"MARKETING") -> 36
B22: 9 | C22: What is the total basic salary of employees from Delta State who are senior officers? | D22: =SUMIFS(Salary_niit!J2:J152,Salary_niit!D2:D152,Salary_niit!D47,Salary_niit!H2:H152,Salary_niit!H113) -> 600000
B24: 10 | C24: What is the highest basic salary | D24: =MAXA(Salary_niit!J2:J152) -> 200000 | E24: =MINA(Salary_niit!J2:J152) -> 100000
B26: 11 | C26: Summarize the total net salary by grade and plot a column chart showing the total net salary for each grades. | D26: GRADE | E26: TOTAL NET SALARY
D27: TRAINEE | E27: =SUMIF(Salary_niit!H2:H152,Salary_niit!H2,Salary_niit!U2:U152) -> 48519400
D28: MANAGER | E28: =SUMIF(Salary_niit!H1:H152,Salary_niit!H137,Salary_niit!U2:U152) -> 24437210
D29: SNR. OFFICER | E29: =SUMIF(Salary_niit!H2:H153,Salary_niit!H138,Salary_niit!U3:U153) -> 50294500
D30: OFFICER | E30: =SUMIF(Salary_niit!H3:H154,Salary_niit!H139,Salary_niit!U4:U154) -> 79051120
D31: SALES SUPERVISOR | E31: =SUMIF(Salary_niit!H4:H155,Salary_niit!H140,Salary_niit!U5:U155) -> 79051120
B38: 12 | C38: Summarize net salary based on department where gender is equal to Female and tax is greater than 10,000
D39: DEPARTMENT | E39: NET SALARY
D40: CREDIT | E40: =SUMIFS(Salary_niit!U2:U152,Salary_niit!F2:F152,DASHBOARD!D40,Salary_niit!E2:E152,Salary_niit!E139,Salary_niit!P2:P152,">10000") -> 6094510
D41: MARKETING | E41: =SUMIFS(Salary_niit!U2:U152,Salary_niit!F2:F152,Salary_niit!F136,Salary_niit!E2:E152,Salary_niit!E146,Salary_niit!P2:P152,">10000") -> 18579380
D42: OPERATIONS | E42: =SUMIFS(Salary_niit!U3:U153,Salary_niit!F3:F153,Salary_niit!F137,Salary_niit!E3:E153,Salary_niit!E147,Salary_niit!P3:P153,">10000") -> 36744570
D43: SECURITY | E43: =SUMIFS(Salary_niit!U4:U154,Salary_niit!F4:F154,Salary_niit!F138,Salary_niit!E4:E154,Salary_niit!E148,Salary_niit!P4:P154,">10000") -> 30886740
D44: SURVELLANCE | E44: =SUMIFS(Salary_niit!U5:U155,Salary_niit!F5:F155,Salary_niit!F139,Salary_niit!E5:E155,Salary_niit!E149,Salary_niit!P5:P155,">10000") -> 4260240
D45: AUDIT | E45: =SUMIFS(Salary_niit!U6:U156,Salary_niit!F6:F156,Salary_niit!F140,Salary_niit!E6:E156,Salary_niit!E150,Salary_niit!P6:P156,">10000") -> 12307360
D46: LEGAL | E46: =SUMIFS(Salary_niit!U7:U157,Salary_niit!F7:F157,Salary_niit!F141,Salary_niit!E7:E157,Salary_niit!E151,Salary_niit!P7:P157,">10000") -> 36744570
D47: TECHNOLOGY | E47: =SUMIFS(Salary_niit!U8:U158,Salary_niit!F8:F158,Salary_niit!F142,Salary_niit!E8:E158,Salary_niit!E152,Salary_niit!P8:P158,">10000") -> 36744570
D48: COMPLIANCE | E48: =SUMIFS(Salary_niit!U9:U159,Salary_niit!F9:F159,Salary_niit!F143,Salary_niit!E9:E159,Salary_niit!E153,Salary_niit!P9:P159,">10000") -> 0
B51: 13 | C51: Identify the grade with the highest average basic salary among female employees from Lagos who have a net salary above ₦1,400,000.
